README.rst
setup.py
waifu.py
waifu_cli.egg-info/PKG-INFO
waifu_cli.egg-info/SOURCES.txt
waifu_cli.egg-info/dependency_links.txt
waifu_cli.egg-info/entry_points.txt
waifu_cli.egg-info/not-zip-safe
waifu_cli.egg-info/pbr.json
waifu_cli.egg-info/requires.txt
waifu_cli.egg-info/top_level.txt