Metadata-Version: 1.1
Name: waifu-cli
Version: 0.0.4
Summary: A simple wrapper for waifu2x.
Home-page: https://github.com/kxxoling/waifu-cli
Author: Kane Blueriver
Author-email: kxxoling@gmail.com
License: MIT
Platform: UNKNOWN
Classifier: Programming Language :: Python
Classifier: Programming Language :: Python :: 2.7
Classifier: Programming Language :: Python :: 3
Classifier: License :: OSI Approved :: MIT License
